timezone_solar/.flake8
timezone_solar/README.md
timezone_solar/__init__.py
timezone_solar/timezone_solar.py
timezone_solar/tzsconst.py
timezone_solar/tests/.flake8
timezone_solar/tests/__init__.py
timezone_solar/tests/__main__.py
timezone_solar/tests/run_tests.py
timezone_solar/tests/test_010_tzsconst.py
timezone_solar/tests/test_011_basic.py
timezone_solar/tests/test_012_latitude.py
timezone_solar/tests/test_013_datetime.py
timezone_solar/tests/utils.py
timezone_solar-0.0.1.dist-info/LICENSE
timezone_solar-0.0.1.dist-info/WHEEL
timezone_solar-0.0.1.dist-info/METADATA
timezone_solar-0.0.1.dist-info/RECORD
