Metadata-Version: 2.1
Name: timezone_solar
Version: 0.0.1
Summary: local solar timezone lookup and utilities including datetime compatibility 
Author-email: Ian Kluft <ko6yq.dev+python@gmail.com>
Requires-Python: >=3.9
Classifier: License :: OSI Approved :: GNU General Public License v3 or later (GPLv3+)
Classifier: Programming Language :: Python :: 3
Classifier: Operating System :: OS Independent
Classifier: Intended Audience :: Developers
Classifier: Topic :: Software Development :: Localization
Project-URL: Bug_Tracker, https://github.com/ikluft/LongitudeTZ/labels/Python
Project-URL: Home, https://github.com/ikluft/LongitudeTZ
Project-URL: Source, https://github.com/ikluft/LongitudeTZ/tree/main/src/python
